hypermodern_python_vb/__init__.py
hypermodern_python_vb/console.py
hypermodern_python_vb/wikipedia.py
hypermodern_python_vb-0.1.0.dist-info/entry_points.txt
hypermodern_python_vb-0.1.0.dist-info/LICENSE
hypermodern_python_vb-0.1.0.dist-info/WHEEL
hypermodern_python_vb-0.1.0.dist-info/METADATA
hypermodern_python_vb-0.1.0.dist-info/RECORD
